opents/__init__.py
opents/data/__init__.py
opents/datasets/__init__.py
opents/datasets/datasets.py
opents/nn/__init__.py
opents/nn/components/__init__.py
opents/nn/components/components.py
opents/nn/detector/__init__.py
opents/nn/detector/openmax.py
opents/nn/loss/__init__.py
opents/nn/loss/logitnorm.py
opents/nn/models/__init__.py
opents/nn/models/fcn.py
opents/nn/models/gan.py
opents/nn/models/opengan.py
opents/utils/__init__.py
opents/utils/data_utils.py
opents/utils/evaluation.py
opents-0.1.3.5.dist-info/METADATA
opents-0.1.3.5.dist-info/WHEEL
opents-0.1.3.5.dist-info/top_level.txt
opents-0.1.3.5.dist-info/RECORD
