Metadata-Version: 2.1
Name: opents
Version: 0.1.3.5
Summary: OpenTS is a friendly Python Library for time series analysis
Home-page: https://github.com/PyOpenTS/PyOpenTS
Author: hushuguo
Author-email: husg8217@mails.jlu.edu.cn
License: MIT
Requires-Dist: torch
Requires-Dist: numpy
Requires-Dist: tqdm
